ab_plugin_scenariolink/__init__.py
ab_plugin_scenariolink/signals.py
ab_plugin_scenariolink/utils.py
ab_plugin_scenariolink/layouts/tabs/__init__.py
ab_plugin_scenariolink/layouts/tabs/right.py
ab_plugin_scenariolink/tables/__init__.py
ab_plugin_scenariolink/tables/models.py
ab_plugin_scenariolink/tables/tables.py
ab_plugin_scenariolink-0.1.0.dist-info/LICENSE.txt
ab_plugin_scenariolink-0.1.0.dist-info/METADATA
ab_plugin_scenariolink-0.1.0.dist-info/WHEEL
ab_plugin_scenariolink-0.1.0.dist-info/top_level.txt
ab_plugin_scenariolink-0.1.0.dist-info/RECORD
