Metadata-Version: 2.1
Name: ab_plugin_scenariolink
Version: 0.1.0
Summary: Activity Browser plugin to download scenario-based LCA databases 
Home-page: https://github.com/polca/ScenarioLink
Author: Romain Sacchi, Marc van der Meide
Author-email: romain.sacchi@psi.ch, m.t.van.der.meide@cml.leidenuniv.nl
License: GNU LESSER GENERAL PUBLIC LICENSE
License-File: LICENSE.txt
Requires-Dist: activity-browser >=2.10.1
Requires-Dist: unfold >=1.2.0
Requires-Dist: datapackage
Requires-Dist: pandas
Requires-Dist: tqdm
